{
  "date": "2026-03-20",
  "total_editorials": 29,
  "total_issues": 13,
  "issues": [
    {
      "issue_name": "수사 / 중수청 / 것이다",
      "keywords": [
        "수사",
        "중수청",
        "것이다",
        "검사의",
        "민주당"
      ],
      "editorial_count": 2,
      "editorials": [
        {
          "press": "조선일보",
          "title": "민생 현장에 광범위한 피해 낳을 중수청, 공소청 법안",
          "link": "https://n.news.naver.com/mnews/article/023/0003965617?sid=110",
          "imageUrl": "https://imgnews.pstatic.net/image/023/2026/03/20/0003965617_001_20260320130212733.JPG?type=w800",
          "snippet": "19일 서울 여의도 국회에서 열린 제433회국회(임시회) 2차 본회의에서 범여권 의원들이 윤상현 국민의힘 의원의 공소청법안(대안)에 대한 무제한토론(필리버스터)이 시작되자 본회의장을 떠나고 있다./뉴스1 민주당이 공소청 설치 법안을 본회의에 상정했다. 중대범죄수사청 설",
          "key_argument": "민주당이 추진하는 중수청·공소청 설치 법안은 검찰의 수사 통제 장치를 제거하여 수사기관 간 혼선과 남용을 야기하고 국민 생활에 광범위한 피해를 줄 수 있다. 제대로 된 공청회 없이 통과되는 과정 자체를 비판한다.",
          "frame": "법치주의, 사법체계",
          "stance": "반대, 비판적",
          "tone": "비판적, 우려, 경고"
        },
        {
          "press": "서울신문",
          "title": "풀보다 먼저 눕는 경찰에 수사권 몰아주기, 與 책임지겠나",
          "link": "https://n.news.naver.com/mnews/article/081/0003627679?sid=110",
          "imageUrl": "https://imgnews.pstatic.net/image/081/2026/03/20/0003627679_001_20260320051317842.jpg?type=w800",
          "snippet": "윤상현 국민의힘 의원이 19일 국회에서 열린 제433회국회(임시회) 2차 본회의에서 공소청법안(대안)에 대한 무제한토론(필리버스터)을 하고 있다. 홍윤기 기자국회는 어제 본회의에서 더불어민주당이 당정협의를 거쳐 제출한 공소청 설치법안을 상정했다. 민주당은 국민의힘의 반",
          "key_argument": "민주당이 검사의 견제 장치를 모두 삭제하고 경찰과 중수청 수사권을 몰아주는 법안을 강행 처리하려는 것은 '검찰수사권 완전박탈' 주장이며, 이는 공소청이 경찰이나 중수청의 '봐주기 수사'나 '과도한 수사'를 통제할 수단을 완전히 사라지게 한다.",
          "frame": "권력 분산, 견제와 균형",
          "stance": "반대, 비판적",
          "tone": "비판적, 우려"
        }
      ],
      "issue_summary": "조선일보와 서울신문은 모두 민주당이 추진하는 중수청 및 공소청 설치 법안에 대해 비판적인 논조를 보이며, 검찰의 수사 기능을 약화시키고 견제 장치를 제거하여 수사기관 간 혼선 및 남용 가능성을 우려한다. 다만, 조선일보는 법안 통과 자체의 문제점을, 서울신문은 경찰에 수사권을 몰아주는 것에 대한 비판에 더 초점을 맞추고 있다."
    },
    {
      "issue_name": "에너지 / 중동 / 원유",
      "keywords": [
        "에너지",
        "중동",
        "원유",
        "이란",
        "공급망"
      ],
      "editorial_count": 4,
      "editorials": [
        {
          "press": "조선일보",
          "title": "중동 위기 장기화 우려, 에너지 소비 억제책 검토할 때",
          "link": "https://n.news.naver.com/mnews/article/023/0003965616?sid=110",
          "imageUrl": "https://imgnews.pstatic.net/image/023/2026/03/20/0003965616_001_20260320001108747.jpg?type=w800",
          "snippet": "산업통상부가 원유 자원안보 위기경보를 '관심'에서 '주의'로 격상한 18일 서울의 한 주유소에 유가정보가 표시되어 있다. / 뉴스1 이란 전쟁에 따른 원유 수급 위기가 생각보다 장기화될 가능성이 생기고 있다. 호르무즈 해협 봉쇄로 다음 달 말이면 중동 지역으로부터 신규",
          "key_argument": "중동발 원유 수급 위기가 장기화될 가능성이 높아 에너지 소비 억제 및 절약 보상 정책으로의 전환이 시급하며, 정부의 가격 누르기 정책은 오히려 에너지 소비를 부추기는 역설을 낳고 있다.",
          "frame": "에너지 수요 관리",
          "stance": "정책 전환 촉구",
          "tone": "우려, 촉구"
        },
        {
          "press": "서울신문",
          "title": "통제 불능 중동 난타전… 출구 없는 오일쇼크 대비 단단히",
          "link": "https://n.news.naver.com/mnews/article/081/0003627677?sid=110",
          "imageUrl": "https://imgnews.pstatic.net/image/081/2026/03/20/0003627677_001_20260320051312333.jpg?type=w800",
          "snippet": "에너지 원자재 공급망도 다변화 필요3高 덮칠 취약계층 안전망 강화해야 중동 전쟁이 에너지 기반 시설 공격전으로 번지면서 국제유가와 원달러 환율이 급등하고 있다. 사진은 19일 서울 중구 하나은행 딜링룸 현황판. 이날 환율은 금융위기 처음으로 주간 거래에서 1500원을 ",
          "key_argument": "미국-이란 전쟁이 에너지 시설 공격으로 격화되면서 국제유가와 환율 급등 등 오일쇼크 가능성이 커졌으므로, 정부는 광범위하고 신속한 대비와 취약계층 안전망 강화에 나서야 한다.",
          "frame": "경제 위기 대비",
          "stance": "대비 촉구",
          "tone": "경고, 촉구"
        },
        {
          "press": "국민일보",
          "title": "에너지 파괴로 가는 이란전, 일관된 자원 안보 전략 중요",
          "link": "https://n.news.naver.com/mnews/article/005/0001838200?sid=110",
          "imageUrl": "https://imgnews.pstatic.net/image/005/2026/03/20/2026031922190517306_1773926345_1773906208_20260320013108603.jpg?type=w800",
          "snippet": "이란 가스전, 카타르 LNG도 피격중동 에너지 의존 많은 韓 타격 커산업 시스템 개선에 전력 기울여야 에미레이트항공 여객기가 지난 16일(현지시간) 아랍에미리트(UAE) 두바이 국제공항으로 착륙을 준비하고 있다. 이날 이란의 드론 공격으로 두바이 국제공항 인근 연료 탱",
          "key_argument": "이란전이 에너지 전면전으로 비화하며 에너지 시설 파괴가 반복되고 있어, 확전으로 인한 글로벌 에너지 시장 충격이 크며, 이에 대한 일관된 자원 안보 전략 수립이 중요하다.",
          "frame": "자원 안보",
          "stance": "전략 중요성 강조",
          "tone": "우려, 강조"
        },
        {
          "press": "한국경제",
          "title": "산업 곳곳 '불가항력' 선언…중동發 공급망 쇼크 막아야",
          "link": "https://n.news.naver.com/mnews/article/015/0005264625?sid=110",
          "imageUrl": "https://ssl.pstatic.net/static.news/image/news/ogtag/navernews_800x420_20221201.jpg",
          "snippet": "미국·이란 전쟁으로 초래된 호르무즈해협 봉쇄가 장기화하면서 ‘불가항력(포스 마주르)’을 선언하며 계약 이행 불가 또는 그럴 가능성을 고객사에 통보하는 국내 기업이 빠르게 늘고 있다는 보도다. 80%를 중동에서 들여오는 나프타 확보에 비상이 걸린 석유화학업계에서 처음 나",
          "key_argument": "호르무즈 해협 봉쇄로 인한 중동발 공급망 위기가 실물 산업 전반에 '불가항력' 선언으로 이어질 만큼 심각하므로, 이를 막기 위한 정부와 기업의 즉각적인 대응이 필요하다.",
          "frame": "공급망 안정",
          "stance": "즉각적 대응 촉구",
          "tone": "경고, 촉구"
        }
      ],
      "issue_summary": "중동발 원유 공급망 위기에 대해 조선일보는 에너지 소비 억제와 수요 관리 정책 전환을, 서울신문은 통제 불능의 중동 사태에 대한 단단한 대비와 취약계층 보호를, 국민일보는 에너지 시설 파괴로 인한 확전 우려와 일관된 자원 안보 전략을, 한국경제는 실물 산업까지 타격하는 공급망 쇼크에 대한 즉각적인 대응을 촉구하며 각각의 문제점을 지적하고 있다."
    },
    {
      "issue_name": "야당 / 상임위원장 / 여야",
      "keywords": [
        "야당",
        "상임위원장",
        "여야",
        "민주당은",
        "민주당"
      ],
      "editorial_count": 2,
      "editorials": [
        {
          "press": "조선일보",
          "title": "마음대로 다하면서 야당 때문에 일 못하겠다니",
          "link": "https://n.news.naver.com/mnews/article/023/0003965615?sid=110",
          "imageUrl": "https://imgnews.pstatic.net/image/023/2026/03/20/0003965615_001_20260320000108699.jpg?type=w800",
          "snippet": "19일 국회에서 열린 3월 임시국회 2차 본회의에서 더불어민주당 정청래 대표가 비례대표 의원직을 승계받은 민주당 김준환 의원등과 기념 촬영하고 있다./연합뉴스 민주당이 19일 공소청법을 국회 본회의에 상정했다. 국민의힘은 필리버스터(무제한 토론)를 통해 법안 반대 의견",
          "key_argument": "민주당이 야당의 의견을 무시하고 법안을 일방 처리하며, 상임위원장 독식까지 거론하며 국정을 운영하는 방식은 권위주의적이며 민주주의 원리에 위배된다. 야당 때문에 일이 안 된다는 주장은 책임 회피일 뿐이다.",
          "frame": "정치독주, 권위주의, 의회주의",
          "stance": "비판적",
          "tone": "강력 비판, 경고"
        },
        {
          "press": "중앙일보",
          "title": "“상임위원장 다 갖겠다”…견제와 균형은 여당 사전에 없나",
          "link": "https://n.news.naver.com/mnews/article/025/0003510370?sid=110",
          "imageUrl": "https://imgnews.pstatic.net/image/025/2026/03/20/0003510370_001_20260320112417738.jpg?type=w800",
          "snippet": "더불어민주당 한병도 원내대표가 19일 국회에서 열린 정책조정회의에서 발언하고 있다. 연합뉴스 더불어민주당이 후반기 국회에서 국회 상임위원장을 모두 차지할 수도 있다면서 국민의힘의 법안 처리 협조를 압박하고 있다. 한병도 민주당 원내대표는 어제 “상임위원장 여야 배분 문",
          "key_argument": "민주당이 국회 상임위원장을 모두 차지하려는 시도는 의회주의의 근간인 견제와 균형 원리를 훼손하는 것으로, 다수 독재로 이어질 위험이 크다. 민생과 개혁을 명분으로 관행을 무시하는 것은 부적절하다.",
          "frame": "의회주의, 견제와 균형, 다수독재",
          "stance": "비판적",
          "tone": "우려, 비판"
        }
      ],
      "issue_summary": "조선일보는 민주당이 법안을 일방 처리하고 사법부까지 종속시키려 한다며 비판한다. 중앙일보는 민주당이 상임위원장 독식을 시사하며 의회주의 원칙을 훼손한다고 지적한다. 두 사설 모두 민주당의 다수 의석을 앞세운 독단적 행태를 비판하고 야당의 견제 기능 약화를 우려한다."
    },
    {
      "issue_name": "사회적 / 고용 / 이재명",
      "keywords": [
        "사회적",
        "고용",
        "이재명",
        "있는",
        "경사노위"
      ],
      "editorial_count": 6,
      "editorials": [
        {
          "press": "중앙일보",
          "title": "노사정 대타협 잘되려면 친노동 정책부터 균형 잡아야",
          "link": "https://n.news.naver.com/mnews/article/025/0003510371?sid=110",
          "imageUrl": "https://imgnews.pstatic.net/image/025/2026/03/20/0003510371_001_20260320112314377.jpg?type=w800",
          "snippet": "이재명 대통령이 19일 청와대 본관에서 열린 경제사회노동위원회 1기 출범 기념 ‘대통령과 함께하는 노동정책 토론회’에서 발언하고 있다. 청와대사진기자단 이재명 대통령이 어제 경제사회노동위원회 1기 출범에 맞춰 열린 노동정책 토론회에서 “노동자들 입장에서 해고는 죽음”이",
          "key_argument": "이재명 대통령이 제시한 덴마크식 유연안정성 모델은 바람직하나, 한국 노동시장의 이중 구조와 일부 노동계의 과잉 보호를 해소하기 위한 현실적 방안 모색이 필요하다.",
          "frame": "노동시장 유연성, 사회안전망",
          "stance": "조건부 찬성",
          "tone": "비판적, 제안적"
        },
        {
          "press": "동아일보",
          "title": "27년간 ‘노사정’ 외면한 민노총… 이젠 대화 테이블로 나오라",
          "link": "https://n.news.naver.com/mnews/article/020/0003705498?sid=110",
          "imageUrl": "https://imgnews.pstatic.net/image/020/2026/03/19/0003705498_001_20260320043717774.jpg?type=w800",
          "snippet": "이재명 대통령이 19일 청와대 본관에서 열린 경제사회노동위원회 1기 출범 기념 ‘대통령과 함께하는 노동정책 토론회’에서 발언하고 있다. 김재명 기자 base@donga.com중동 사태로 원-달러 환율이 1500원을 넘는 위기 상황에서 이재명 정부의 1기 경제사회노동위원",
          "key_argument": "경사노위 출범은 환영하지만, 과거 민주노총의 외면과 현재의 경직된 노동시장으로는 AI 시대의 과제를 해결하기 어렵다. 노사정 대타협을 통해 유연성 확보와 사회안전망 강화를 이루어야 한다.",
          "frame": "노사정 대화, 노동시장 개혁",
          "stance": "촉구",
          "tone": "비판적, 촉구"
        },
        {
          "press": "경향신문",
          "title": "경사노위 새 출범, ‘AI 시대 노사 상생’ 청사진 만들길",
          "link": "https://n.news.naver.com/mnews/article/032/0003434423?sid=110",
          "imageUrl": "https://imgnews.pstatic.net/image/032/2026/03/19/0003434423_001_20260319214612659.jpeg?type=w800",
          "snippet": "이재명 대통령이 19일 청와대 본관에서 열린 경제사회노동위원회 1기 출범 기념 ‘대통령과 함께하는 노동정책 토론회’에서 발언하고 있다. 김창길 기자 이재명 정부 1기 경제사회노동위원회가 19일 출범했다. 경사노위가 재가동하는 건 12·3 내란 이후 15개월 만이다. 그",
          "key_argument": "경사노위 재가동은 노동존중사회 구현의 출발점으로, AI 시대의 노사 상생과 일자리 문제 해결을 위한 실질적인 청사진을 제시해야 한다.",
          "frame": "노사 상생, AI 시대",
          "stance": "기대, 촉구",
          "tone": "긍정적, 촉구"
        },
        {
          "press": "한국일보",
          "title": "공론장 오른 고용 유연성, 노사 한 발씩 양보해야",
          "link": "https://n.news.naver.com/mnews/article/469/0000920524?sid=110",
          "imageUrl": "https://imgnews.pstatic.net/image/469/2026/03/20/0000920524_001_20260320061319898.jpg?type=w800",
          "snippet": "이재명 대통령이 19일 청와대 본관에서 열린 경제사회노동위원회 1기 출범 기념 ‘대통령과 함께하는 노동정책 토론회’에서 손경식 한국경영자총연합회 회장의 이야기를 듣고 있다. 왕태석 선임기자이재명 대통령은 19일 \"기업이 원하는 고용 유연성에 대해 노동자들이 수용할 수 ",
          "key_argument": "고용 유연성 논의를 본격화한 것은 긍정적이며, 노동시장 이중 구조 해소와 청년 일자리 문제를 위해 노사 모두 한 발씩 양보하고 사회안전망을 강화해야 한다.",
          "frame": "고용 유연성, 노동시장 양극화",
          "stance": "찬성, 촉구",
          "tone": "중립적, 제안적"
        },
        {
          "press": "서울경제",
          "title": "李정부 첫 경사노위 출범…기업·노조·AI 상생의 길 터야",
          "link": "https://n.news.naver.com/mnews/article/011/0004601369?sid=110",
          "imageUrl": "https://imgnews.pstatic.net/image/011/2026/03/20/0004601369_001_20260320000608681.jpg?type=w800",
          "snippet": "이재명 대통령이 19일 경제사회노동위원회 제1기 출범을 맞이해 청와대에서 열린 노동정책 토론회에서 참석자들의 발언을 듣고 있다. 연합뉴스노사정 사회적 대화를 이끌어 갈 이재명 정부의 제1기 경제사회노동위원회가 19일 출범했다. 경사노위는 이날 청와대에서 첫 회의를 열고",
          "key_argument": "경사노위 출범과 노동 유연성·사회안전망 균형점 모색은 시의적절하나, 노란봉투법 시행 등 왜곡된 노사 관계와 해외 기업 사례를 볼 때 현대차 노조의 입장은 우려스럽다.",
          "frame": "노사 협력, AI 시대",
          "stance": "환영, 우려",
          "tone": "긍정적, 비판적"
        },
        {
          "press": "한국경제",
          "title": "AI전환·청년일자리…경사노위, 선언 넘어 해법 도출을",
          "link": "https://n.news.naver.com/mnews/article/015/0005264628?sid=110",
          "imageUrl": "https://ssl.pstatic.net/static.news/image/news/ogtag/navernews_800x420_20221201.jpg",
          "snippet": "이재명 정부 제1기 경제사회노동위원회가 ‘사회적 대화 2.0’이라는 슬로건 아래 어제 출범했다. 1999년 탈퇴한 민주노총에 이어 한국노총마저 윤석열 정부의 노동개혁을 반대하며 보이콧을 선언한 2023년 이후 멈춰섰던 노사 대화 시계가 다시 작동하는 것이다. 노사정 대",
          "key_argument": "경사노위 재가동은 반갑지만, 선언에 그치지 않고 AI 전환, 청년 일자리 등 복합 대전환 시기의 해법을 도출해야 한다. 이재명 대통령의 유연성 확대 및 사회안전망 구축 제안은 시의적절하다.",
          "frame": "사회적 대화, AI 전환",
          "stance": "기대, 촉구",
          "tone": "긍정적, 기대"
        }
      ],
      "issue_summary": "이재명 정부의 경제사회노동위원회(경사노위) 출범과 노동시장 유연성 및 사회안전망 강화 방안에 대한 사설들은 경사노위 재가동을 긍정적으로 평가하며 AI 시대의 과제 해결을 촉구한다. 다만, 경사노위의 실질적 역할과 노사정 간 입장 차이에 대한 톤은 각 매체별로 다소 상이하다."
    },
    {
      "issue_name": "컴백 / 광화문 / 공연을",
      "keywords": [
        "컴백",
        "광화문",
        "공연을",
        "세계",
        "안전"
      ],
      "editorial_count": 2,
      "editorials": [
        {
          "press": "중앙일보",
          "title": "세계 이목 쏠린 BTS 공연, K컬처 한 단계 업그레이드 계기로",
          "link": "https://n.news.naver.com/mnews/article/025/0003510369?sid=110",
          "imageUrl": "https://imgnews.pstatic.net/image/025/2026/03/20/0003510369_001_20260320112421966.jpg?type=w800",
          "snippet": "방탄소년단(BTS) 컴백 공연을 이틀 앞둔 19일 서울 종로구 광화문광장 인근 빌딩 전광판에 컴백 공연을 알리는 광고가 표출되고 있다. 김종호 기자 내일(21일) 오후 서울 광화문 일대가 세계인의 시선이 집중되는 거대 야외 공연장이 된다. 3년9개월 만에 7명 완전체가",
          "key_argument": "BTS 컴백 공연은 K헤리티지를 세계에 각인시킬 절호의 기회이며, 광화문이라는 역사적 공간에서의 공연은 그 의미를 더한다.",
          "frame": "문화 콘텐츠, 국가 브랜드",
          "stance": "찬성, 긍정적",
          "tone": "기대, 옹호"
        },
        {
          "press": "한국일보",
          "title": "26만 광화문 운집 BTS 공연, 세계에 K 저력 보여줄 기회",
          "link": "https://n.news.naver.com/mnews/article/469/0000920525?sid=110",
          "imageUrl": "https://imgnews.pstatic.net/image/469/2026/03/20/0000920525_001_20260320061125694.jpg?type=w800",
          "snippet": "BTS 컴백 공연을 이틀 앞둔 19일 서울 종로구 광화문광장 일대가 일찌감치 모여든 BTS 팬들로 북적이고 있다. 윤기훈 인턴기자21일 오후 서울 광화문광장에서 열리는 그룹 방탄소년단(BTS) 컴백 공연에는 26만 명 이상 인파가 몰려들 것으로 예상된다. 관광업계에 따",
          "key_argument": "26만 명 이상의 인파가 예상되는 BTS 컴백 공연은 K팝의 저력을 세계에 알리고 상당한 경제적 파급효과를 가져올 기회이나, 안전 관리가 완벽히 이루어져야 한다.",
          "frame": "경제 효과, 안전 관리",
          "stance": "조건부 찬성, 신중론",
          "tone": "기회 강조, 우려"
        }
      ],
      "issue_summary": "중앙일보는 BTS 컴백 공연을 K팝과 한국 문화유산을 세계에 알릴 문화적 기회로 보고 긍정적으로 평가하는 반면, 한국일보는 막대한 경제적 효과와 함께 현장 안전 관리의 중요성을 강조하며 균형 잡힌 시각을 제시한다."
    },
    {
      "issue_name": "숨진 / 울산 / 벼랑",
      "keywords": [
        "숨진",
        "울산",
        "벼랑",
        "울주군의",
        "그의"
      ],
      "editorial_count": 1,
      "editorials": [
        {
          "press": "동아일보",
          "title": "울산 4자녀, 군산 모자의 비극… 죽어야 보이는 ‘벼랑 끝 사람들’",
          "link": "https://n.news.naver.com/mnews/article/020/0003705497?sid=110",
          "imageUrl": "https://imgnews.pstatic.net/image/020/2026/03/19/0003705497_001_20260320052815240.jpg?type=w800",
          "snippet": "19일 오전 울산 울주군의 한 빌라 현관문에 ‘출입금지’라고 적힌 폴리스라인이 쳐져있다. 울주=뉴스118일 울산 울주군의 한 다가구 주택에서 30대 남성과 그의 어린 네 자녀가 숨진 채 발견됐다. 경찰은 아내가 범죄에 연루돼 수감된 후 혼자 생계와 육아를 맡아 온 남성",
          "key_argument": "울산 4자녀 및 군산 모자 사건과 같이 안타까운 죽음이 반복되는 것은 사회 안전망의 허점을 여실히 보여주며, 사전에 이상 징후를 감지하고도 적극적으로 개입하지 못한 책임을 묻고 있다. '벼랑 끝 사람들'에 대한 더 세심한 관심과 지원 시스템의 확충을 촉구한다.",
          "frame": "사회안전망, 복지 사각지대, 아동 보호",
          "stance": "비판적, 촉구",
          "tone": "안타까움, 우려, 촉구"
        }
      ],
      "issue_summary": "울산 4자녀 및 군산 모자 사건을 통해 사회 안전망의 사각지대를 조명하며, 국가와 사회가 '벼랑 끝 사람들'에 대한 더 적극적인 개입과 지원의 필요성을 강조하고 있다. 다만, 각 신문사별로 사안의 경중이나 강조점에 미세한 차이를 보이고 있다."
    },
    {
      "issue_name": "대구 / 대구시장 / 국민의힘",
      "keywords": [
        "대구",
        "대구시장",
        "국민의힘",
        "이정현",
        "주호영"
      ],
      "editorial_count": 2,
      "editorials": [
        {
          "press": "동아일보",
          "title": "민심은 흉흉한데 텃밭 공천 두고 아귀다툼하는 국힘",
          "link": "https://n.news.naver.com/mnews/article/020/0003705496?sid=110",
          "imageUrl": "https://imgnews.pstatic.net/image/020/2026/03/19/0003705496_001_20260320043725526.jpg?type=w800",
          "snippet": "대구시장 선거에 뛰어든 국민의힘 6선 중진 주호영 의원(왼쪽), 이정현 공천관리위원장. 뉴시스 국민의힘의 6·3 지방선거 후보 공천이 저질 막말과 후보 내정설 등에 휩싸이며 ‘진흙탕 싸움’으로 변질되고 있다. 이정현 공천관리위원장이 세대교체를 내세우며 대구시장 경선에서",
          "key_argument": "국민의힘 대구시장 공천 과정에서 중진 의원들이 텃밭을 두고 벌이는 '아귀다툼'은 국민의 기대에 부응하지 못하는 행태이며, 당내 갈등과 막말이 민심을 흉흉하게 만들고 있다.",
          "frame": "정치개혁, 공천 쇄신",
          "stance": "비판적",
          "tone": "비판적, 우려"
        },
        {
          "press": "한국일보",
          "title": "막장으로 가는 국민의힘 대구 밥그릇 싸움",
          "link": "https://n.news.naver.com/mnews/article/469/0000920522?sid=110",
          "imageUrl": "https://imgnews.pstatic.net/image/469/2026/03/20/0000920522_001_20260320061138701.jpg?type=w800",
          "snippet": "2016년 8월 새누리당(국민의힘 전신) 전당대회를 앞두고 당대표 선거에 출마한 주호영(왼쪽), 이정현 후보가 여의도 당사에서 만나 악수하고 있다. 이들은 10년이 지나 지방선거 대구시장 공천을 놓고 앙숙이 됐다. 서재훈 기자대구가 6·3 지방선거 격전지로 떠올랐다. ",
          "key_argument": "국민의힘 대구시장 공천을 둘러싼 갈등은 지역감정을 자극하는 '막장 싸움'으로 변질되어 유권자의 환멸을 사고 있으며, 당내 밥그릇 싸움에 몰두하는 모습은 대구 민심의 이탈을 초래할 수 있다.",
          "frame": "정치 기강, 민심 소통",
          "stance": "비판적",
          "tone": "비판적, 경고"
        }
      ],
      "issue_summary": "동아일보는 국민의힘의 대구시장 공천 과정에서 벌어지는 중진 의원들의 텃밭 싸움과 이에 대한 이정현 공관위원장의 대응을 비판하며, 당내 갈등이 민심을 얻지 못하고 있다고 지적합니다. 한국일보는 이 갈등이 지역감정을 자극하는 '막장 싸움'으로 변질되었으며, 이는 유권자의 환멸을 초래할 뿐 아니라 대구 민심의 이탈을 야기할 수 있다고 비판적인 논조를 보입니다."
    },
    {
      "issue_name": "에너지 / 시설에 / 세계",
      "keywords": [
        "에너지",
        "시설에",
        "세계",
        "공격을",
        "트럼프"
      ],
      "editorial_count": 1,
      "editorials": [
        {
          "press": "한겨레",
          "title": "세계 경제 파탄 막으려면, 에너지 시설 공격은 멈춰야",
          "link": "https://n.news.naver.com/mnews/article/028/0002796767?sid=110",
          "imageUrl": "https://imgnews.pstatic.net/image/028/2026/03/19/0002796767_001_20260320023404367.jpg?type=w800",
          "snippet": "도널드 트럼프 미국 대통령이 18일(현지시각) 워싱턴 백악관 야외 공간에서 피트 헤그세스 국방부(전쟁부) 장관(가운데), 댄 케인 합참의장(오른쪽)과 대화하고 있다. 이후 세 사람은 지난 12일 이라크 서부 상공에서 발생한 케이시(KC)-135 공중급유기 추락 사고의 ",
          "key_argument": "에너지 시설에 대한 무책임한 공격이 세계 경제에 더 큰 파탄을 가져올 수 있으므로 즉각 중단되어야 한다. 트럼프 대통령의 중재 노력에도 불구하고 상황이 악화되는 것을 막아야 한다.",
          "frame": "경제 안정, 국제 협력",
          "stance": "비판적 (에너지 시설 공격에 대해), 촉구 (평화적 해결)",
          "tone": "우려, 경고, 촉구"
        }
      ],
      "issue_summary": "한겨레 사설은 이란과 이스라엘 간 에너지 시설 공격으로 인한 세계 경제 파탄을 우려하며, 트럼프 대통령의 중재 노력을 언급하며 더 이상의 확전을 막아야 한다는 점을 강조한다. 사설은 에너지 시설 공격이 세계 경제에 미치는 부정적 영향에 초점을 맞추고 있다."
    },
    {
      "issue_name": "달러 / 금리 / 연준",
      "keywords": [
        "달러",
        "금리",
        "연준",
        "에너지",
        "파월"
      ],
      "editorial_count": 3,
      "editorials": [
        {
          "press": "한겨레",
          "title": "환율 17년만에 1500원 돌파, 금융·외환시장 안정 총력을",
          "link": "https://n.news.naver.com/mnews/article/028/0002796747?sid=110",
          "imageUrl": "https://imgnews.pstatic.net/image/028/2026/03/19/0002796747_001_20260320023314508.jpg?type=w800",
          "snippet": "19일 오후 서울 중구 하나은행 딜링룸 현황판에 원-달러 환율과 코스피 지수가 표시돼 있다. 연합뉴스 미국-이란 전쟁이 격화하면서 원-달러 환율이 결국 달러당 1500원을 넘어섰다. 주간거래 종가 기준으로 환율이 1500원을 돌파한 것은 글로벌 금융위기 당시인 2009",
          "key_argument": "미국-이란 전쟁 격화로 원-달러 환율이 1500원을 돌파한 상황에서 금융·외환시장 안정과 경제 주체들의 심리 안정에 당국이 총력을 기울여야 한다.",
          "frame": "금융시장 안정, 경제 심리",
          "stance": "비판적, 촉구",
          "tone": "우려, 촉구"
        },
        {
          "press": "경향신문",
          "title": "중동 석유시설로 확전, 에너지·공급망·환율 비상대책 짜야",
          "link": "https://n.news.naver.com/mnews/article/032/0003434429?sid=110",
          "imageUrl": "https://imgnews.pstatic.net/image/032/2026/03/19/0003434429_001_20260319214507590.png?type=w800",
          "snippet": "지난 2일(현지시간) 카타르 라스라판 산업도시 내 카타르에너지의 액화천연가스(LNG) 생산 시설 전경. 로이터연합뉴스미국·이스라엘과 이란 전쟁이 ‘레드라인’으로 여겨온 에너지 생산 인프라까지 서로 공습하는 전면전으로 치닫고 있다. 국제유가 급등과 인플레이션 우려에 세계",
          "key_argument": "미국-이란 전쟁이 에너지 시설로 확전되어 국제유가 급등과 인플레이션 우려가 커진 만큼, 사태 장기화에 대비한 에너지, 공급망, 환율 관련 특단의 비상 대책 마련이 시급하다.",
          "frame": "에너지 안보, 공급망 관리",
          "stance": "비판적, 촉구",
          "tone": "비상, 촉구"
        },
        {
          "press": "서울경제",
          "title": "파월 “전쟁 영향 아무도 몰라”, 최악 상황까지 대비를",
          "link": "https://n.news.naver.com/mnews/article/011/0004601370?sid=110",
          "imageUrl": "https://imgnews.pstatic.net/image/011/2026/03/20/0004601370_001_20260320000612236.jpg?type=w800",
          "snippet": "제롬 파월 미국 연방준비제도 의장이 18일 이틀간의 연방공개시장위원회(FOMC) 회의 후 기자회견을 하고 있다. 로이터=연합뉴스미국 연방준비제도(Fed·연준)가 18일 기준금리를 연 3.50~3.75%로 올 1월에 이어 또다시 동결했다. 강한 인플레이션 압박 때문인 것",
          "key_argument": "중동 전쟁의 파급력과 연준의 금리 동결, 물가 상승 등의 상황을 볼 때, 최악의 스태그플레이션 상황까지 대비하며 시장의 불안감을 해소할 다각적인 대응이 필요하다.",
          "frame": "경제 위기 관리, 금리 정책",
          "stance": "비판적, 신중론",
          "tone": "경고, 우려"
        }
      ],
      "issue_summary": "세 신문사는 모두 중동 전쟁 발발로 인한 국제유가 급등, 환율 상승, 물가 인상 우려 등 복합적인 위기 상황에 대한 심각성을 강조하며 정부 및 관련 기관의 총력 대응을 촉구하고 있습니다. 다만, 한겨레는 금융시장 안정에, 경향신문은 에너지·공급망 비상 대책에, 서울경제는 최악의 상황까지 대비해야 한다는 점을 좀 더 부각하며 미묘한 논조 차이를 보입니다."
    },
    {
      "issue_name": "개헌 / 원내대표 / 우원식",
      "keywords": [
        "개헌",
        "원내대표",
        "우원식",
        "헌법에",
        "국민의힘은"
      ],
      "editorial_count": 1,
      "editorials": [
        {
          "press": "한겨레",
          "title": "점진적·단계적 개헌 늦출 이유 없어, 국힘도 협조해야",
          "link": "https://n.news.naver.com/mnews/article/028/0002796743?sid=110",
          "imageUrl": "https://imgnews.pstatic.net/image/028/2026/03/19/0002796743_001_20260320023308712.jpg?type=w800",
          "snippet": "우원식 국회의장이 19일 국회의장실에서 원내 6개 정당 원내대표와 회동하기에 앞서 기념 촬영을 하고 있다. 국민의힘은 불참했다. 왼쪽부터 기본소득당 용혜인 원내대표, 진보당 윤종오 원내대표, 더불어민주당 한병도 원내대표, 우원식 국회의장, 조국혁신당 서왕진 원내대표, ",
          "key_argument": "우원식 국회의장이 제안한 점진적·단계적 개헌 논의는 국회 구성원 다수의 지지를 얻었으며, 국민적 여론도 뒷받침되므로 국민의힘은 개헌 논의에 협조해야 한다.",
          "frame": "정치개혁, 민주주의",
          "stance": "조건부 찬성 (점진적·단계적 개헌 논의에 대한 지지 및 국민의힘 참여 촉구)",
          "tone": "촉구, 비판적"
        }
      ],
      "issue_summary": "한겨레 사설은 우원식 국회의장의 제안으로 시작된 점진적·단계적 개헌 논의에 대해 긍정적인 평가를 내리며, 개헌 논의에 불참한 국민의힘을 비판하고 협조를 촉구하고 있다. 개헌에 대한 국민적 지지를 바탕으로 국민의힘의 참여를 거듭 강조하는 논조이다."
    },
    {
      "issue_name": "종묘 / 세운 / 국가유산청이",
      "keywords": [
        "종묘",
        "세운",
        "국가유산청이",
        "매장유산",
        "시추"
      ],
      "editorial_count": 1,
      "editorials": [
        {
          "press": "경향신문",
          "title": "종묘 앞 개발 갈등 격화, 유네스코 실사부터 순리 따르라",
          "link": "https://n.news.naver.com/mnews/article/032/0003434424?sid=110",
          "imageUrl": "https://imgnews.pstatic.net/image/032/2026/03/19/0003434424_001_20260319214609839.jpg?type=w800",
          "snippet": "국가유산청이 지난 16일 “세운4구역의 사업시행자인 서울주택도시개발공사(SH)를 매장유산 보호 및 조사에 관한 법률 위반 협의로 경찰에 고발했다”고 밝혔다. 사진은 SH가 서울 종묘 옆 세운4구역 도시환경정비사업부지 내 11곳을 시추하는 모습. 국가유산청 제공. 서울 ",
          "key_argument": "SH의 종묘 부근 매장유산 유존지 무단 시추는 매장유산법 위반이자 문화유산 훼손 행위이며, 공공행정의 오만과 독선을 보여주는 개탄스러운 일이다. 국제사회 경고와 법적 대응에도 공사 강행 의지를 굽히지 않는 서울시와 SH는 순리에 따라 유네스코 실사 등 절차를 존중해야 한다.",
          "frame": "문화유산 보호, 법치주의, 공공행정 비판",
          "stance": "비판적, 반대",
          "tone": "비판적, 경고, 개탄"
        }
      ],
      "issue_summary": "경향신문은 종묘 앞 세운4구역 재개발 사업에서 SH의 무단 시추를 매장유산법 위반이자 공공행정의 오만으로 규정하며, 문화유산 훼손 행위에 대한 법적 대응과 국제 기준 준수를 촉구하고 있다. 서울시와 SH의 공사 강행 의지를 비판하며 유네스코 실사 등 순리에 따를 것을 강조한다."
    },
    {
      "issue_name": "북한 / 대북 / 위협",
      "keywords": [
        "북한",
        "대북",
        "위협",
        "북한은",
        "북한이"
      ],
      "editorial_count": 3,
      "editorials": [
        {
          "press": "서울신문",
          "title": "美 “북핵 중대 위협”에도 비핵화 뺀 공존, 꿈보다 해몽인가",
          "link": "https://n.news.naver.com/mnews/article/081/0003627678?sid=110",
          "imageUrl": "https://imgnews.pstatic.net/image/081/2026/03/20/0003627678_001_20260320051315149.png?type=w800",
          "snippet": "한미연합훈련 - 19일 끝난 한미 연합 지휘소훈련(CPX)인 ‘자유의 방패’(프리덤실드·FS) 연습에서 최신 방공체계이자 ‘미국판 아이언돔’으로 불리는 간접화력방어체계(IFPC)의 운용 장면이 처음 공개됐다. 지난해 9월 주한미군에 처음 배치된 IFPC는 해외 미군 기",
          "key_argument": "정부의 남북관계발전계획에서 북한 비핵화를 제외하고 평화 공존을 강조하는 것은 불안한 안보 현실을 외면한 대책 없는 낙관이며, 대북 안보 태세를 흔들 수 있다.",
          "frame": "안보, 외교",
          "stance": "비판적",
          "tone": "우려, 경고"
        },
        {
          "press": "서울경제",
          "title": "美 “北 중대 위협” 경고에도 ‘文 대북정책’ 회귀하나",
          "link": "https://n.news.naver.com/mnews/article/011/0004601371?sid=110",
          "imageUrl": "https://imgnews.pstatic.net/image/011/2026/03/20/0004601371_001_20260320000615397.jpg?type=w800",
          "snippet": "정동영 통일부 장관이 19일 정부서울청사에서 남북관계발전위원회 전체회의를 열고 5차 남북관계발전기본계획 심의를 진행하고 있다. 연합뉴스미국 국가정보국(DNI)이 18일 ‘2026년 연례위협평가 보고서’를 통해 “북한은 미국 전역에 도달할 수 있는 대륙간탄도미사일(ICB",
          "key_argument": "미국의 북한 ICBM 성공 평가와 중대 위협 경고에도 불구하고, 정부가 비핵화를 앞세웠던 이전 계획을 폐기하고 평화 공존 제도화를 추진하는 것은 과거 정부 정책으로 회귀하는 것과 같다.",
          "frame": "안보, 외교",
          "stance": "비판적",
          "tone": "경고, 비판"
        },
        {
          "press": "국민일보",
          "title": "전쟁 경험 쌓는 북한… 축소된 훈련으로 대응 충분한가",
          "link": "https://n.news.naver.com/mnews/article/005/0001838199?sid=110",
          "imageUrl": "https://imgnews.pstatic.net/image/005/2026/03/20/2026031922210517312_1773926465_1773900750_20260320012108522.jpg?type=w800",
          "snippet": "北, 러-우 전쟁 참여로 실전 경험 축적미사일·드론·사이버 결합 입체위협훈련 줄여 만든 대화 여건, 공백은 없나 지난 14일 경기도 연천군 임진강에서 실시된 한미연합 도하훈련에서 미군 시누크 헬기가 부교를 공중 수송하고 있다. 한미연합훈련 '자유의 방패'(프리덤실드·F",
          "key_argument": "러시아-우크라이나 전쟁 참여로 북한이 실전 경험을 축적하고 자신감을 높이는 상황에서, 훈련을 축소하여 대응하는 것은 충분하지 않으며 공백을 야기할 수 있다.",
          "frame": "안보, 군사",
          "stance": "비판적",
          "tone": "우려, 경고"
        }
      ],
      "issue_summary": "세 사설 모두 북한의 핵·미사일 위협 증가를 경고하며, 정부의 대북 정책 방향에 대해 우려를 표하고 있다. 특히 서울신문과 서울경제는 정부의 '평화 공존' 기조가 비핵화와 인권 문제를 간과하고 과거 정부의 정책과 유사하다는 점을 비판하는 반면, 국민일보는 북한의 실전 경험 축적과 자신감 고조를 지적하며 축소된 훈련으로 대응하는 것에 대한 우려를 제기한다."
    },
    {
      "issue_name": "줄기세포 / 국내 / 바이오",
      "keywords": [
        "줄기세포",
        "국내",
        "바이오",
        "세포",
        "개발한"
      ],
      "editorial_count": 1,
      "editorials": [
        {
          "press": "한국경제",
          "title": "한국 건너뛰고 일본서 '첫 허가' 받은 K줄기세포 치료제",
          "link": "https://n.news.naver.com/mnews/article/015/0005264626?sid=110",
          "imageUrl": "https://ssl.pstatic.net/static.news/image/news/ogtag/navernews_800x420_20221201.jpg",
          "snippet": "국내 바이오 기업이 개발한 피부 유전질환 줄기세포 치료제가 일본에서 정식 품목 허가를 받는다는 소식이다. 코스닥시장 상장사인 안트로젠이 개발한 ‘알로스템’이 지난주 일본 의약품의료기기종합기구(PMDA) 심의를 통과했다. 후생노동성이 허가 사실을 고시하면 알로스템은 일본",
          "key_argument": "국내 바이오 기업의 줄기세포 치료제가 일본에서 먼저 허가받은 것은 성과지만, 국내 규제와 시장 규모의 한계로 인한 현상으로, 국내 규제 완화와 제도 개선이 시급하다.",
          "frame": "규제 개선, 시장 성장",
          "stance": "비판적, 개혁 촉구",
          "tone": "우려, 촉구"
        }
      ],
      "issue_summary": "한국 바이오 기업이 개발한 줄기세포 치료제가 국내 규제와 시장 규모의 한계로 인해 일본에서 먼저 허가를 받은 상황에 대해, 한국경제는 이를 아쉬운 성과로 평가하며 국내 규제 개선의 필요성을 강조한다. 특히 희소질환 치료제의 국내 시장 규모와 건강보험 적용 기준의 한계, 그리고 엄격한 국내 규제가 해외 원정 치료를 야기한다고 지적하며 규제 완화를 촉구하는 논조를 보인다."
    }
  ]
}